uifunc/__init__.py
uifunc/common_file_types.py
uifunc/qtopen.py
uifunc/tkopen.py
uifunc/wxopen.py
uifunc-0.1.6.dist-info/DESCRIPTION.rst
uifunc-0.1.6.dist-info/METADATA
uifunc-0.1.6.dist-info/RECORD
uifunc-0.1.6.dist-info/WHEEL
uifunc-0.1.6.dist-info/metadata.json
uifunc-0.1.6.dist-info/top_level.txt
