Metadata-Version: 2.0
Name: uifunc
Version: 0.1.6
Summary: convenience functions for opening and saving files/folders
Home-page: https://github.com/Palpatineli/uifunc
Author: Keji Li
Author-email: mail@keji.li
License: GPLv3
Download-URL: https://github.com/Palpatineli/uifunc/archive/0.1.5.tar.gz
Platform: UNKNOWN
Classifier: Development Status :: 4 - Beta
Classifier: Programming Language :: Python :: 3
Provides-Extra: qt
Provides-Extra: wx
Provides-Extra: qt
Requires-Dist: PyQt5; extra == 'qt'
Provides-Extra: wx
Requires-Dist: wx; extra == 'wx'
